AUTHORS
CHANGES.rst
LICENSE
MANIFEST.in
README.rst
setup.py
example/__init__.py
example/my_calculate.py
example/my_string.py
example/test/__init__.py
example/test/lesson8_Sample_module.py
example/test/test_example.py
example/test/test_lesson8_yaml_testbed.oot
example/test/test_lesson8_yaml_testbed.py
example/test/test_number.oot
example/test/test_string.py
example/test/test_usestep.py
example/test/testbed.py
pytest_oot/__init__.py
pytest_oot/oot_plugin.py
pytest_oot.egg-info/PKG-INFO
pytest_oot.egg-info/SOURCES.txt
pytest_oot.egg-info/dependency_links.txt
pytest_oot.egg-info/entry_points.txt
pytest_oot.egg-info/requires.txt
pytest_oot.egg-info/top_level.txt